pythonwhois/__init__.py
pythonwhois/airports.dat
pythonwhois/common_first_names.dat
pythonwhois/countries.dat
pythonwhois/countries3.dat
pythonwhois/net.py
pythonwhois/parse.py
pythonwhois/shared.py
pythonwhois/states_au.dat
pythonwhois/states_ca.dat
pythonwhois/states_us.dat
pythonwhois/caching/__init__.py
pythonwhois/caching/whois_server_cache.py
pythonwhois/ratelimit/__init__.py
pythonwhois/ratelimit/cool_down.py
pythonwhois/ratelimit/cool_down_config.py
pythonwhois/ratelimit/cool_down_tracker.py
pythonwhois/response/__init__.py
pythonwhois/response/final_whois_results.py
pythonwhois/response/raw_response_holder.py
pythonwhois/response/raw_whois_response.py
pythonwhois/response/whois_results.py
whois_oracle-1.1.4.data/scripts/whois-oracle
whois_oracle-1.1.4.dist-info/DESCRIPTION.rst
whois_oracle-1.1.4.dist-info/METADATA
whois_oracle-1.1.4.dist-info/RECORD
whois_oracle-1.1.4.dist-info/WHEEL
whois_oracle-1.1.4.dist-info/metadata.json
whois_oracle-1.1.4.dist-info/top_level.txt
