Metadata-Version: 2.0
Name: whois-oracle
Version: 1.1.4
Summary: Module for retrieving and parsing the WHOIS data for a domain. Supports most domains. No dependencies.
Home-page: https://github.com/MasterFenrir/whois-oracle
Author: Sander ten Hoor, original by Sven Slootweg
Author-email: UNKNOWN
License: WTFPL
Keywords: whois cool down
Platform: UNKNOWN
Provides: pythonwhois
Requires-Dist: argparse
